ioihelper/__init__.py
ioihelper/ioihelper_cli.py
ioihelper/ioihelper_core.py
ioihelper/data/__init__.py
ioihelper-0.7.3.dist-info/licenses/LICENSE
ioihelper-0.7.3.dist-info/METADATA
ioihelper-0.7.3.dist-info/WHEEL
ioihelper-0.7.3.dist-info/entry_points.txt
ioihelper-0.7.3.dist-info/top_level.txt
ioihelper-0.7.3.dist-info/RECORD
