Metadata-Version: 2.4
Name: ioihelper
Version: 0.7.3
Summary: Edits and updates Islands of Insight save game files to make your offline experience more fun.
Author-email: Robin Fredericksen <refredericksen@gmail.com>
License-Expression: CC-BY-NC-SA-4.0
Project-URL: Homepage, https://github.com/Ryzhara/IslandsOfInsightHelper
Project-URL: Source, https://github.com/Ryzhara/IslandsOfInsightHelper.git
Project-URL: LibrarySource, https://github.com/Ryzhara/pygvas.git
Project-URL: Tracker, https://github.com/Ryzhara/IslandsOfInsightHelper/issues
Project-URL: SteamGame, https://store.steampowered.com/app/2071500/Islands_of_Insight/
Requires-Python: >=3.9
License-File: LICENSE
Requires-Dist: pygvas>=0.9.3
Requires-Dist: jsonpath_ng>=1.7.0
Dynamic: license-file
